{
    "configurations": [
        {
            "name": "Mac",
            "includePath": [
                "${workspaceFolder}/**",
                "/Users/mstampe/esp/v5.4.1/esp-idf/components/**"
            ],
            "defines": [],
            "compilerPath": "/usr/bin/clang",
            "cStandard": "c17",
            "cppStandard": "c++17",
            "intelliSenseMode": "macos-clang-arm64",
            "configurationProvider": "espressif.esp-idf-extension"
        }
    ],
    "version": 4
}